datetype/__init__.py
datetype/py.typed
datetype/test/__init__.py
datetype/test/test_datetype.py
datetype-2025.10.9.dist-info/licenses/LICENSE.txt
datetype-2025.10.9.dist-info/METADATA
datetype-2025.10.9.dist-info/WHEEL
datetype-2025.10.9.dist-info/top_level.txt
datetype-2025.10.9.dist-info/RECORD
